{
  "2157": {
    "name": "コシダカホールディングス",
    "zaiko": {
      "nikko": 1900,
      "kabucom": null,
      "rakuten": null,
      "sbi": null,
      "gmo": null,
      "matsui": null,
      "monex": 1
    },
    "taisyaku": "貸借銘柄",
    "is_taishaku": true,
    "kabuka": 1254,
    "kabusu": 100,
    "max_gyaku": 1040,
    "gyaku_days": 1,
    "avg5_gyaku": 1.6,
    "haito": 13,
    "gl_value": 1000,
    "yutai": "【100株】買物券 2000円相当",
    "yutai_syubetsu": "買物券",
    "restriction": "",
    "d_kenri": "8月31日",
    "updated": "2026-01-13T09:54:34.674626"
  },
  "2164": {
    "name": "地域新聞社",
    "zaiko": {
      "nikko": null,
      "kabucom": null,
      "rakuten": null,
      "sbi": null,
      "gmo": null,
      "matsui": null,
      "monex": null
    },
    "taisyaku": "制度信用銘柄",
    "is_taishaku": false,
    "kabuka": 256,
    "kabusu": 100,
    "max_gyaku": 400,
    "gyaku_days": 1,
    "avg5_gyaku": 0.0,
    "haito": 0,
    "gl_value": 0,
    "yutai": "【100株】「ちいきの逸品」割引券など",
    "yutai_syubetsu": "割引券",
    "restriction": "",
    "d_kenri": "2月末<br>8月31日",
    "updated": "2026-01-13T09:54:34.674639"
  },
  "2186": {
    "name": "ソーバル",
    "zaiko": {
      "nikko": null,
      "kabucom": null,
      "rakuten": null,
      "sbi": null,
      "gmo": null,
      "matsui": null,
      "monex": null
    },
    "taisyaku": "制度信用銘柄",
    "is_taishaku": false,
    "kabuka": 0,
    "kabusu": 100,
    "max_gyaku": 400,
    "gyaku_days": 1,
    "avg5_gyaku": 0.0,
    "haito": null,
    "gl_value": 475,
    "yutai": "【100株】クオカード500円相当",
    "yutai_syubetsu": "クオカード",
    "restriction": "",
    "d_kenri": "8月31日",
    "updated": "2026-01-13T09:54:34.674644"
  },
  "2292": {
    "name": "Ｓ　Ｆｏｏｄｓ",
    "zaiko": {
      "nikko": 4000,
      "kabucom": 79200,
      "rakuten": 0,
      "sbi": null,
      "gmo": null,
      "matsui": 2,
      "monex": 1
    },
    "taisyaku": "貸借銘柄",
    "is_taishaku": true,
    "kabuka": 2765,
    "kabusu": 100,
    "max_gyaku": 2240,
    "gyaku_days": 1,
    "avg5_gyaku": 3.335,
    "haito": null,
    "gl_value": 0,
    "yutai": "【100株】自社グループ商品の優待価格販売",
    "yutai_syubetsu": "自社サービス",
    "restriction": "",
    "d_kenri": "2月末日<br>8月31日",
    "updated": "2026-01-13T09:54:34.674649"
  },
  "2305": {
    "name": "スタジオアリス",
    "zaiko": {
      "nikko": 700,
      "kabucom": null,
      "rakuten": null,
      "sbi": null,
      "gmo": null,
      "matsui": null,
      "monex": 1
    },
    "taisyaku": "貸借銘柄",
    "is_taishaku": true,
    "kabuka": 2024,
    "kabusu": 100,
    "max_gyaku": 1680,
    "gyaku_days": 1,
    "avg5_gyaku": 8.33,
    "haito": null,
    "gl_value": 3000,
    "yutai": "【100株】写真撮影券",
    "yutai_syubetsu": "自社サービス",
    "restriction": "",
    "d_kenri": "8月31日",
    "updated": "2026-01-13T09:54:34.674654"
  },
  "2337": {
    "name": "いちご",
    "zaiko": {
      "nikko": 800,
      "kabucom": 940400,
      "rakuten": 0,
      "sbi": null,
      "gmo": null,
      "matsui": 2,
      "monex": 1
    },
    "taisyaku": "貸借銘柄",
    "is_taishaku": true,
    "kabuka": 453,
    "kabusu": 1,
    "max_gyaku": 4,
    "gyaku_days": 1,
    "avg5_gyaku": 0.165,
    "haito": null,
    "gl_value": 0,
    "yutai": "【1株】【抽選】Ｊリーグ観戦チケット",
    "yutai_syubetsu": "自社サービス",
    "restriction": "",
    "d_kenri": "2月末日<br>8月31日",
    "updated": "2026-01-13T09:54:34.674659"
  },
  "2379": {
    "name": "ディップ",
    "zaiko": {
      "nikko": 500,
      "kabucom": null,
      "rakuten": null,
      "sbi": null,
      "gmo": null,
      "matsui": 2,
      "monex": 1
    },
    "taisyaku": "貸借銘柄",
    "is_taishaku": true,
    "kabuka": 2251,
    "kabusu": 100,
    "max_gyaku": 1840,
    "gyaku_days": 1,
    "avg5_gyaku": 2.035,
    "haito": null,
    "gl_value": 475,
    "yutai": "【100株】クオカード 500円相当",
    "yutai_syubetsu": "クオカード",
    "restriction": "",
    "d_kenri": "2月末日<br>8月31日",
    "updated": "2026-01-13T09:54:34.674663"
  },
  "2404": {
    "name": "鉄人化ホールディングス",
    "zaiko": {
      "nikko": null,
      "kabucom": null,
      "rakuten": null,
      "sbi": null,
      "gmo": null,
      "matsui": null,
      "monex": null
    },
    "taisyaku": "貸借銘柄",
    "is_taishaku": true,
    "kabuka": 508,
    "kabusu": 100,
    "max_gyaku": 480,
    "gyaku_days": 1,
    "avg5_gyaku": 13.76,
    "haito": 0,
    "gl_value": 900,
    "yutai": "【100株】グループご優待券 3000円相当など",
    "yutai_syubetsu": "買物券",
    "restriction": "",
    "d_kenri": "8月31日",
    "updated": "2026-01-13T09:54:34.674667"
  },
  "245A": {
    "name": "ＩＮＧＳ",
    "zaiko": {
      "nikko": null,
      "kabucom": null,
      "rakuten": null,
      "sbi": null,
      "gmo": null,
      "matsui": null,
      "monex": null
    },
    "taisyaku": "制度信用銘柄",
    "is_taishaku": false,
    "kabuka": 0,
    "kabusu": 100,
    "max_gyaku": 400,
    "gyaku_days": 1,
    "avg5_gyaku": 0.0,
    "haito": 0,
    "gl_value": 0,
    "yutai": "【100株】食事券(電子チケット)2,000円相当",
    "yutai_syubetsu": "買物券",
    "restriction": "",
    "d_kenri": "2月末<br>8月31日",
    "updated": "2026-01-13T09:54:34.674671"
  },
  "2669": {
    "name": "カネ美食品",
    "zaiko": {
      "nikko": null,
      "kabucom": null,
      "rakuten": null,
      "sbi": null,
      "gmo": null,
      "matsui": null,
      "monex": null
    },
    "taisyaku": "貸借銘柄",
    "is_taishaku": true,
    "kabuka": 3545,
    "kabusu": 100,
    "max_gyaku": 2880,
    "gyaku_days": 1,
    "avg5_gyaku": 60.355,
    "haito": null,
    "gl_value": 1800,
    "yutai": "【100株】セレクトグルメ配達便 3000円相当",
    "yutai_syubetsu": "カタログギフト",
    "restriction": "",
    "d_kenri": "2月末日<br>8月31日",
    "updated": "2026-01-13T09:54:34.674674"
  },
  "2683": {
    "name": "魚喜",
    "zaiko": {
      "nikko": null,
      "kabucom": null,
      "rakuten": null,
      "sbi": null,
      "gmo": null,
      "matsui": null,
      "monex": null
    },
    "taisyaku": "制度信用銘柄",
    "is_taishaku": false,
    "kabuka": 996,
    "kabusu": 100,
    "max_gyaku": 800,
    "gyaku_days": 1,
    "avg5_gyaku": 0.0,
    "haito": null,
    "gl_value": 600,
    "yutai": "【100株】オリジナルカレー 2個セット",
    "yutai_syubetsu": "食べ物",
    "restriction": "",
    "d_kenri": "8月31日",
    "updated": "2026-01-13T09:54:34.674678"
  },
  "2685": {
    "name": "アンドエスティＨＤ",
    "zaiko": {
      "nikko": 3800,
      "kabucom": 100300,
      "rakuten": 0,
      "sbi": null,
      "gmo": null,
      "matsui": null,
      "monex": null
    },
    "taisyaku": "貸借銘柄",
    "is_taishaku": true,
    "kabuka": 2854,
    "kabusu": 100,
    "max_gyaku": 2320,
    "gyaku_days": 1,
    "avg5_gyaku": 3.745,
    "haito": null,
    "gl_value": 0,
    "yutai": "【100株】【2026開始】株主様ご優待券1500円",
    "yutai_syubetsu": "買物券",
    "restriction": "",
    "d_kenri": "2月末日<br>8月31日",
    "updated": "2026-01-13T09:54:34.674683"
  },
  "2686": {
    "name": "ジーフット",
    "zaiko": {
      "nikko": 0,
      "kabucom": null,
      "rakuten": null,
      "sbi": null,
      "gmo": null,
      "matsui": null,
      "monex": null
    },
    "taisyaku": "制度信用銘柄",
    "is_taishaku": false,
    "kabuka": 0,
    "kabusu": 100,
    "max_gyaku": 400,
    "gyaku_days": 1,
    "avg5_gyaku": 0.0,
    "haito": null,
    "gl_value": 550,
    "yutai": "【100株】買物券 1000円相当",
    "yutai_syubetsu": "買物券",
    "restriction": "",
    "d_kenri": "2月末日<br>8月31日",
    "updated": "2026-01-13T09:54:34.674687"
  },
  "2687": {
    "name": "シー・ヴイ・エス・ベイエリア",
    "zaiko": {
      "nikko": 0,
      "kabucom": null,
      "rakuten": null,
      "sbi": null,
      "gmo": null,
      "matsui": null,
      "monex": null
    },
    "taisyaku": "貸借銘柄",
    "is_taishaku": true,
    "kabuka": 516,
    "kabusu": 100,
    "max_gyaku": 480,
    "gyaku_days": 1,
    "avg5_gyaku": 0.795,
    "haito": null,
    "gl_value": 0,
    "yutai": "【100株】宿泊割引券(1,000円)",
    "yutai_syubetsu": "割引券",
    "restriction": "",
    "d_kenri": "2月末日<br>8月31日",
    "updated": "2026-01-13T09:54:34.674690"
  },
  "2698": {
    "name": "キャンドゥ",
    "zaiko": {
      "nikko": 0,
      "kabucom": null,
      "rakuten": 0,
      "sbi": null,
      "gmo": null,
      "matsui": null,
      "monex": null
    },
    "taisyaku": "貸借銘柄",
    "is_taishaku": true,
    "kabuka": 3430,
    "kabusu": 100,
    "max_gyaku": 2800,
    "gyaku_days": 1,
    "avg5_gyaku": 0.36,
    "haito": null,
    "gl_value": 1892,
    "yutai": "【100株】買物券 2200円相当",
    "yutai_syubetsu": "買物券",
    "restriction": "停止",
    "d_kenri": "8月31日",
    "updated": "2026-01-13T09:54:34.674695"
  },
  "2736": {
    "name": "フェスタリアホールディングス",
    "zaiko": {
      "nikko": null,
      "kabucom": null,
      "rakuten": null,
      "sbi": null,
      "gmo": null,
      "matsui": null,
      "monex": null
    },
    "taisyaku": "制度信用銘柄",
    "is_taishaku": false,
    "kabuka": 0,
    "kabusu": 300,
    "max_gyaku": 1200,
    "gyaku_days": 1,
    "avg5_gyaku": 0.0,
    "haito": 7,
    "gl_value": 2000,
    "yutai": "【300株】自社商品10,000円相当 もしくは 割引クーポン15,000円分",
    "yutai_syubetsu": "自社商品",
    "restriction": "",
    "d_kenri": "8月31日",
    "updated": "2026-01-13T09:54:34.674699"
  },
  "274A": {
    "name": "ガーデン",
    "zaiko": {
      "nikko": null,
      "kabucom": null,
      "rakuten": null,
      "sbi": null,
      "gmo": null,
      "matsui": null,
      "monex": null
    },
    "taisyaku": "制度信用銘柄",
    "is_taishaku": false,
    "kabuka": 2263,
    "kabusu": 100,
    "max_gyaku": 1840,
    "gyaku_days": 1,
    "avg5_gyaku": 0.0,
    "haito": null,
    "gl_value": 0,
    "yutai": "【100株】全商品１品無料券 1枚【注：継続保有制限】",
    "yutai_syubetsu": "買物券",
    "restriction": "",
    "d_kenri": "2月末<br>8月31日",
    "updated": "2026-01-13T09:54:34.674703"
  },
  "2798": {
    "name": "ワイズテーブルコーポレーション",
    "zaiko": {
      "nikko": null,
      "kabucom": null,
      "rakuten": null,
      "sbi": null,
      "gmo": null,
      "matsui": null,
      "monex": null
    },
    "taisyaku": "制度信用銘柄",
    "is_taishaku": false,
    "kabuka": 2995,
    "kabusu": 100,
    "max_gyaku": 2400,
    "gyaku_days": 1,
    "avg5_gyaku": 0.0,
    "haito": null,
    "gl_value": 2825,
    "yutai": "【100株】株主優待券 5000円相当",
    "yutai_syubetsu": "買物券",
    "restriction": "",
    "d_kenri": "2月末<br>8月31日",
    "updated": "2026-01-13T09:54:34.674706"
  },
  "2872": {
    "name": "セイヒョー",
    "zaiko": {
      "nikko": null,
      "kabucom": null,
      "rakuten": null,
      "sbi": null,
      "gmo": null,
      "matsui": null,
      "monex": 0
    },
    "taisyaku": "制度信用銘柄",
    "is_taishaku": false,
    "kabuka": 2053,
    "kabusu": 100,
    "max_gyaku": 1680,
    "gyaku_days": 1,
    "avg5_gyaku": 0.0,
    "haito": null,
    "gl_value": 800,
    "yutai": "【100株】アイスなど自社製品2,000円相当",
    "yutai_syubetsu": "自社商品",
    "restriction": "",
    "d_kenri": "8月31日",
    "updated": "2026-01-13T09:54:34.674710"
  },
  "2882": {
    "name": "イートアンドホールディングス",
    "zaiko": {
      "nikko": 0,
      "kabucom": null,
      "rakuten": null,
      "sbi": null,
      "gmo": null,
      "matsui": null,
      "monex": null
    },
    "taisyaku": "貸借銘柄",
    "is_taishaku": true,
    "kabuka": 2044,
    "kabusu": 100,
    "max_gyaku": 1680,
    "gyaku_days": 1,
    "avg5_gyaku": 18.19,
    "haito": null,
    "gl_value": 0,
    "yutai": "【100株】大阪王将公式通販クーポン券2,000円相当",
    "yutai_syubetsu": "買物券",
    "restriction": "",
    "d_kenri": "2月末日<br>8月31日",
    "updated": "2026-01-13T09:54:34.674714"
  },
  "2884": {
    "name": "ヨシムラ・フード・ホールディングス",
    "zaiko": {
      "nikko": 1000,
      "kabucom": null,
      "rakuten": 0,
      "sbi": null,
      "gmo": null,
      "matsui": null,
      "monex": 1
    },
    "taisyaku": "貸借銘柄",
    "is_taishaku": true,
    "kabuka": 740,
    "kabusu": 2500,
    "max_gyaku": 16000,
    "gyaku_days": 1,
    "avg5_gyaku": 2.18,
    "haito": null,
    "gl_value": 1600,
    "yutai": "【2500株】自社グループ商品4000円相当【注：継続保有制限】",
    "yutai_syubetsu": "自社商品",
    "restriction": "",
    "d_kenri": "2月末日<br>8月31日",
    "updated": "2026-01-13T09:54:34.674718"
  },
  "2901": {
    "name": "ウェルディッシュ",
    "zaiko": {
      "nikko": null,
      "kabucom": null,
      "rakuten": null,
      "sbi": null,
      "gmo": null,
      "matsui": null,
      "monex": null
    },
    "taisyaku": "制度信用銘柄",
    "is_taishaku": false,
    "kabuka": 458,
    "kabusu": 300,
    "max_gyaku": 1200,
    "gyaku_days": 1,
    "avg5_gyaku": 0.0,
    "haito": 4,
    "gl_value": 0,
    "yutai": "【300株】クオカード5000円相当\t【注：継続保有制限】",
    "yutai_syubetsu": "クオカード",
    "restriction": "",
    "d_kenri": "3月31日<br>9月30日",
    "updated": "2026-01-13T09:54:34.674722"
  },
  "2927": {
    "name": "ＡＦＣ－ＨＤアムスライフサイエンス",
    "zaiko": {
      "nikko": null,
      "kabucom": null,
      "rakuten": null,
      "sbi": null,
      "gmo": null,
      "matsui": null,
      "monex": 1
    },
    "taisyaku": "制度信用銘柄",
    "is_taishaku": false,
    "kabuka": 891,
    "kabusu": 1000,
    "max_gyaku": 7200,
    "gyaku_days": 1,
    "avg5_gyaku": 0.0,
    "haito": 18,
    "gl_value": 1600,
    "yutai": "【1000株】通販カタログ商品引換券5000円分など",
    "yutai_syubetsu": "買物券",
    "restriction": "",
    "d_kenri": "2月末日<br>8月31日",
    "updated": "2026-01-13T09:54:34.674726"
  },
  "2936": {
    "name": "ベースフード",
    "zaiko": {
      "nikko": null,
      "kabucom": null,
      "rakuten": null,
      "sbi": null,
      "gmo": null,
      "matsui": null,
      "monex": null
    },
    "taisyaku": "貸借銘柄",
    "is_taishaku": true,
    "kabuka": 327,
    "kabusu": 100,
    "max_gyaku": 400,
    "gyaku_days": 1,
    "avg5_gyaku": 0.05,
    "haito": null,
    "gl_value": 0,
    "yutai": "【100株】公式ホームページで利用可能な総額1,500円分のご優待クーポン",
    "yutai_syubetsu": "買物券",
    "restriction": "",
    "d_kenri": "8月31日",
    "updated": "2026-01-13T09:54:34.674730"
  },
  "2972": {
    "name": "サンケイリアルエステート投資法人",
    "zaiko": {
      "nikko": null,
      "kabucom": null,
      "rakuten": null,
      "sbi": null,
      "gmo": null,
      "matsui": null,
      "monex": null
    },
    "taisyaku": "制度信用銘柄",
    "is_taishaku": false,
    "kabuka": 0,
    "kabusu": 1,
    "max_gyaku": 4,
    "gyaku_days": 1,
    "avg5_gyaku": 0.0,
    "haito": null,
    "gl_value": 0,
    "yutai": "【1株】インターゲートホテルズ宿泊優待（5％）",
    "yutai_syubetsu": "自社サービス",
    "restriction": "",
    "d_kenri": "2月末<br>8月31日",
    "updated": "2026-01-13T09:54:34.674733"
  },
  "2999": {
    "name": "ホームポジション",
    "zaiko": {
      "nikko": null,
      "kabucom": null,
      "rakuten": null,
      "sbi": null,
      "gmo": null,
      "matsui": null,
      "monex": 1
    },
    "taisyaku": "制度信用銘柄",
    "is_taishaku": false,
    "kabuka": 490,
    "kabusu": 1000,
    "max_gyaku": 4000,
    "gyaku_days": 1,
    "avg5_gyaku": 0.0,
    "haito": 10,
    "gl_value": 19000,
    "yutai": "【1000株】【2025】クオカード20000円相当",
    "yutai_syubetsu": "クオカード",
    "restriction": "",
    "d_kenri": "8月31日",
    "updated": "2026-01-13T09:54:34.674737"
  },
  "3045": {
    "name": "カワサキ",
    "zaiko": {
      "nikko": null,
      "kabucom": null,
      "rakuten": null,
      "sbi": null,
      "gmo": null,
      "matsui": null,
      "monex": null
    },
    "taisyaku": "制度信用銘柄",
    "is_taishaku": false,
    "kabuka": 1501,
    "kabusu": 100,
    "max_gyaku": 1280,
    "gyaku_days": 1,
    "avg5_gyaku": 0.0,
    "haito": 25,
    "gl_value": 0,
    "yutai": "【100株】オンラインショップクーポン1,500円 及び アルザ泉大津」ご利用券1,500円",
    "yutai_syubetsu": "買物券",
    "restriction": "",
    "d_kenri": "2月末<br>8月31日",
    "updated": "2026-01-13T09:54:34.674741"
  },
  "3046": {
    "name": "ジンズホールディングス",
    "zaiko": {
      "nikko": 900,
      "kabucom": 3300,
      "rakuten": 8000,
      "sbi": null,
      "gmo": null,
      "matsui": 2,
      "monex": 2
    },
    "taisyaku": "貸借銘柄",
    "is_taishaku": true,
    "kabuka": 5290,
    "kabusu": 100,
    "max_gyaku": 4240,
    "gyaku_days": 1,
    "avg5_gyaku": 5.67,
    "haito": 68,
    "gl_value": 4500,
    "yutai": "【100株】買物券 9000円相当",
    "yutai_syubetsu": "買物券",
    "restriction": "",
    "d_kenri": "8月31日",
    "updated": "2026-01-13T09:54:34.674746"
  },
  "3048": {
    "name": "ビックカメラ",
    "zaiko": {
      "nikko": 4200,
      "kabucom": 14800,
      "rakuten": 0,
      "sbi": null,
      "gmo": 2,
      "matsui": 2,
      "monex": 1
    },
    "taisyaku": "貸借銘柄",
    "is_taishaku": true,
    "kabuka": 1705,
    "kabusu": 100,
    "max_gyaku": 1440,
    "gyaku_days": 1,
    "avg5_gyaku": 2.77,
    "haito": 21,
    "gl_value": 920,
    "yutai": "【100株】株主様お買物優待券1000円相当",
    "yutai_syubetsu": "買物券",
    "restriction": "",
    "d_kenri": "2月末日<br>8月31日",
    "updated": "2026-01-13T09:54:34.674751"
  },
  "3063": {
    "name": "ジェイグループホールディングス",
    "zaiko": {
      "nikko": null,
      "kabucom": null,
      "rakuten": null,
      "sbi": null,
      "gmo": null,
      "matsui": null,
      "monex": null
    },
    "taisyaku": "貸借銘柄",
    "is_taishaku": true,
    "kabuka": 820,
    "kabusu": 100,
    "max_gyaku": 720,
    "gyaku_days": 1,
    "avg5_gyaku": 17.71,
    "haito": null,
    "gl_value": 0,
    "yutai": "【100株】お食事優待券2,000円分",
    "yutai_syubetsu": "買物券",
    "restriction": "",
    "d_kenri": "2月末日<br>8月31日",
    "updated": "2026-01-13T09:54:34.674755"
  },
  "3065": {
    "name": "ライフフーズ",
    "zaiko": {
      "nikko": null,
      "kabucom": null,
      "rakuten": null,
      "sbi": null,
      "gmo": null,
      "matsui": null,
      "monex": null
    },
    "taisyaku": "制度信用銘柄",
    "is_taishaku": false,
    "kabuka": 0,
    "kabusu": 100,
    "max_gyaku": 400,
    "gyaku_days": 1,
    "avg5_gyaku": 0.0,
    "haito": null,
    "gl_value": 440,
    "yutai": "【100株】ジェフグルメカード 500円相当など",
    "yutai_syubetsu": "ギフトカード",
    "restriction": "",
    "d_kenri": "2月末日<br>8月31日",
    "updated": "2026-01-13T09:54:34.674758"
  },
  "3083": {
    "name": "スターシーズ",
    "zaiko": {
      "nikko": null,
      "kabucom": null,
      "rakuten": null,
      "sbi": null,
      "gmo": null,
      "matsui": null,
      "monex": null
    },
    "taisyaku": "制度信用銘柄",
    "is_taishaku": false,
    "kabuka": 810,
    "kabusu": 100,
    "max_gyaku": 720,
    "gyaku_days": 1,
    "avg5_gyaku": 0.0,
    "haito": null,
    "gl_value": 0,
    "yutai": "【100株】株主優待クーポン券1500円相当",
    "yutai_syubetsu": "買物券",
    "restriction": "",
    "d_kenri": "8月31日",
    "updated": "2026-01-13T09:54:34.674762"
  },
  "3086": {
    "name": "Ｊ．フロント　リテイリング",
    "zaiko": {
      "nikko": 4800,
      "kabucom": 727200,
      "rakuten": 0,
      "sbi": 1,
      "gmo": null,
      "matsui": 2,
      "monex": 2
    },
    "taisyaku": "貸借銘柄",
    "is_taishaku": true,
    "kabuka": 2251,
    "kabusu": 100,
    "max_gyaku": 1840,
    "gyaku_days": 1,
    "avg5_gyaku": 0.61,
    "haito": null,
    "gl_value": 2000,
    "yutai": "【100株】買物優待カード10%【新規株主のみ】",
    "yutai_syubetsu": "割引券",
    "restriction": "",
    "d_kenri": "2月末日<br>8月31日",
    "updated": "2026-01-13T09:54:34.674766"
  },
  "3168": {
    "name": "ＭＥＲＦ",
    "zaiko": {
      "nikko": 0,
      "kabucom": null,
      "rakuten": null,
      "sbi": null,
      "gmo": null,
      "matsui": null,
      "monex": 1
    },
    "taisyaku": "貸借銘柄",
    "is_taishaku": true,
    "kabuka": 681,
    "kabusu": 100,
    "max_gyaku": 560,
    "gyaku_days": 1,
    "avg5_gyaku": 10.59,
    "haito": 10,
    "gl_value": 475,
    "yutai": "【100株】クオカード 500円相当",
    "yutai_syubetsu": "クオカード",
    "restriction": "",
    "d_kenri": "8月31日",
    "updated": "2026-01-13T09:54:34.674770"
  },
  "3189": {
    "name": "ＡＮＡＰホールディングス",
    "zaiko": {
      "nikko": null,
      "kabucom": null,
      "rakuten": null,
      "sbi": null,
      "gmo": null,
      "matsui": null,
      "monex": null
    },
    "taisyaku": "制度信用銘柄",
    "is_taishaku": false,
    "kabuka": 0,
    "kabusu": 100,
    "max_gyaku": 400,
    "gyaku_days": 1,
    "avg5_gyaku": 0.0,
    "haito": 0,
    "gl_value": 20,
    "yutai": "【100株】優待割引券（30%割引）2枚",
    "yutai_syubetsu": "割引券",
    "restriction": "",
    "d_kenri": "8月31日",
    "updated": "2026-01-13T09:54:34.674774"
  },
  "3198": {
    "name": "ＳＦＰホールディングス",
    "zaiko": {
      "nikko": 0,
      "kabucom": null,
      "rakuten": 0,
      "sbi": null,
      "gmo": null,
      "matsui": null,
      "monex": null
    },
    "taisyaku": "制度信用銘柄",
    "is_taishaku": false,
    "kabuka": 2210,
    "kabusu": 100,
    "max_gyaku": 1840,
    "gyaku_days": 1,
    "avg5_gyaku": 0.0,
    "haito": null,
    "gl_value": 2400,
    "yutai": "【100株】食事券 4000円相当",
    "yutai_syubetsu": "買物券",
    "restriction": "",
    "d_kenri": "2月末日<br>8月31日",
    "updated": "2026-01-13T09:54:34.674778"
  },
  "3222": {
    "name": "ユナイテッド・スーパーマーケット・ホール",
    "zaiko": {
      "nikko": 6100,
      "kabucom": 0,
      "rakuten": 0,
      "sbi": null,
      "gmo": null,
      "matsui": null,
      "monex": 1
    },
    "taisyaku": "貸借銘柄",
    "is_taishaku": true,
    "kabuka": 889,
    "kabusu": 100,
    "max_gyaku": 720,
    "gyaku_days": 1,
    "avg5_gyaku": 4.015,
    "haito": null,
    "gl_value": 900,
    "yutai": "【100株】買物券3000円相当など",
    "yutai_syubetsu": "買物券",
    "restriction": "",
    "d_kenri": "2月末日<br>8月31日",
    "updated": "2026-01-13T09:54:34.674782"
  },
  "325A": {
    "name": "ＴＥＮＴＩＡＬ",
    "zaiko": {
      "nikko": null,
      "kabucom": null,
      "rakuten": null,
      "sbi": null,
      "gmo": null,
      "matsui": null,
      "monex": null
    },
    "taisyaku": "貸借銘柄",
    "is_taishaku": true,
    "kabuka": 4850,
    "kabusu": 100,
    "max_gyaku": 3920,
    "gyaku_days": 1,
    "avg5_gyaku": 0.0,
    "haito": 0,
    "gl_value": 0,
    "yutai": "【100株】オンラインストア及び直営店舗クーポン2,000円相当【注：継続保有制限】",
    "yutai_syubetsu": "買物券",
    "restriction": "注意",
    "d_kenri": "2月末<br>8月31日",
    "updated": "2026-01-13T09:54:34.674787"
  },
  "3344": {
    "name": "null",
    "zaiko": {
      "nikko": null,
      "kabucom": null,
      "rakuten": null,
      "sbi": null,
      "gmo": null,
      "matsui": null,
      "monex": null
    },
    "taisyaku": "",
    "is_taishaku": false,
    "kabuka": 0,
    "kabusu": 100,
    "max_gyaku": 400,
    "gyaku_days": 1,
    "avg5_gyaku": 0.0,
    "haito": null,
    "gl_value": 1600,
    "yutai": "【100株】優待ポイント 2000円相当",
    "yutai_syubetsu": "買物券",
    "restriction": "",
    "d_kenri": "8月31日",
    "updated": "2026-01-13T09:54:34.674790"
  },
  "3376": {
    "name": "null",
    "zaiko": {
      "nikko": null,
      "kabucom": null,
      "rakuten": null,
      "sbi": null,
      "gmo": null,
      "matsui": null,
      "monex": null
    },
    "taisyaku": "",
    "is_taishaku": false,
    "kabuka": 0,
    "kabusu": 100,
    "max_gyaku": 400,
    "gyaku_days": 1,
    "avg5_gyaku": 0.0,
    "haito": null,
    "gl_value": 10,
    "yutai": "【100株】割引券20%",
    "yutai_syubetsu": "割引券",
    "restriction": "",
    "d_kenri": "8月31日",
    "updated": "2026-01-13T09:54:34.674794"
  },
  "3387": {
    "name": "クリエイト・レストランツ・ホールディング",
    "zaiko": {
      "nikko": 6100,
      "kabucom": null,
      "rakuten": 0,
      "sbi": 1,
      "gmo": null,
      "matsui": null,
      "monex": null
    },
    "taisyaku": "貸借銘柄",
    "is_taishaku": true,
    "kabuka": 791,
    "kabusu": 100,
    "max_gyaku": 640,
    "gyaku_days": 1,
    "avg5_gyaku": 5.92,
    "haito": null,
    "gl_value": 1280,
    "yutai": "【100株】【2026より変更あり】買物券 2000円相当",
    "yutai_syubetsu": "買物券",
    "restriction": "",
    "d_kenri": "2月末日<br>８月31日",
    "updated": "2026-01-13T09:54:34.674799"
  },
  "3396": {
    "name": "フェリシモ",
    "zaiko": {
      "nikko": 0,
      "kabucom": null,
      "rakuten": null,
      "sbi": null,
      "gmo": null,
      "matsui": null,
      "monex": 1
    },
    "taisyaku": "制度信用銘柄",
    "is_taishaku": false,
    "kabuka": 0,
    "kabusu": 100,
    "max_gyaku": 400,
    "gyaku_days": 1,
    "avg5_gyaku": 0.0,
    "haito": null,
    "gl_value": 500,
    "yutai": "【100株】食品・生活雑貨など 1000円相当",
    "yutai_syubetsu": "食べ物",
    "restriction": "",
    "d_kenri": "8月31日",
    "updated": "2026-01-13T09:54:34.674803"
  },
  "3490": {
    "name": "アズ企画設計",
    "zaiko": {
      "nikko": null,
      "kabucom": null,
      "rakuten": null,
      "sbi": null,
      "gmo": null,
      "matsui": null,
      "monex": null
    },
    "taisyaku": "制度信用銘柄",
    "is_taishaku": false,
    "kabuka": 3165,
    "kabusu": 100,
    "max_gyaku": 2560,
    "gyaku_days": 1,
    "avg5_gyaku": 0.0,
    "haito": null,
    "gl_value": 2850,
    "yutai": "【100株】【2026より継続保有制限】クオカード4000円相当",
    "yutai_syubetsu": "クオカード",
    "restriction": "",
    "d_kenri": "2月末日<br>8月31日",
    "updated": "2026-01-13T09:54:34.674806"
  },
  "3498": {
    "name": "霞ヶ関キャピタル",
    "zaiko": {
      "nikko": null,
      "kabucom": null,
      "rakuten": null,
      "sbi": null,
      "gmo": null,
      "matsui": null,
      "monex": null
    },
    "taisyaku": "貸借銘柄",
    "is_taishaku": true,
    "kabuka": 7450,
    "kabusu": 100,
    "max_gyaku": 6000,
    "gyaku_days": 1,
    "avg5_gyaku": 3.81,
    "haito": 165,
    "gl_value": 3000,
    "yutai": "【100株】【2026変更あり】プレミアム優待クラブ5000ポイント",
    "yutai_syubetsu": "プレミアム優待クラブ",
    "restriction": "",
    "d_kenri": "8月31日",
    "updated": "2026-01-13T09:54:34.674812"
  },
  "3536": {
    "name": "アクサスホールディングス",
    "zaiko": {
      "nikko": null,
      "kabucom": null,
      "rakuten": null,
      "sbi": null,
      "gmo": null,
      "matsui": null,
      "monex": null
    },
    "taisyaku": "制度信用銘柄",
    "is_taishaku": false,
    "kabuka": 128,
    "kabusu": 1000,
    "max_gyaku": 4000,
    "gyaku_days": 1,
    "avg5_gyaku": 0.0,
    "haito": 2,
    "gl_value": 5000,
    "yutai": "【1000株】六甲山ピュアモルトウイスキー「ＭＩＺＵＮＡＲＡ」など【注：継続保有制限】",
    "yutai_syubetsu": "食べ物",
    "restriction": "",
    "d_kenri": "8月31日",
    "updated": "2026-01-13T09:54:34.674826"
  },
  "3543": {
    "name": "コメダホールディングス",
    "zaiko": {
      "nikko": 4700,
      "kabucom": 71000,
      "rakuten": 0,
      "sbi": null,
      "gmo": null,
      "matsui": 2,
      "monex": 1
    },
    "taisyaku": "貸借銘柄",
    "is_taishaku": true,
    "kabuka": 3025,
    "kabusu": 100,
    "max_gyaku": 2480,
    "gyaku_days": 1,
    "avg5_gyaku": 2.07,
    "haito": null,
    "gl_value": 800,
    "yutai": "【100株】株主優待電子マネー(コメカカード) 1000円相当",
    "yutai_syubetsu": "買物券",
    "restriction": "",
    "d_kenri": "2月末日<br>8月31日",
    "updated": "2026-01-13T09:54:34.674831"
  },
  "3548": {
    "name": "バロックジャパンリミテッド",
    "zaiko": {
      "nikko": 5400,
      "kabucom": null,
      "rakuten": 0,
      "sbi": null,
      "gmo": null,
      "matsui": null,
      "monex": null
    },
    "taisyaku": "貸借銘柄",
    "is_taishaku": true,
    "kabuka": 787,
    "kabusu": 100,
    "max_gyaku": 640,
    "gyaku_days": 1,
    "avg5_gyaku": 4.115,
    "haito": null,
    "gl_value": 750,
    "yutai": "【100株】クーポン 2000円相当",
    "yutai_syubetsu": "買物券",
    "restriction": "",
    "d_kenri": "2月末日<br>8月31日",
    "updated": "2026-01-13T09:54:34.674836"
  },
  "3556": {
    "name": "リネットジャパングループ",
    "zaiko": {
      "nikko": null,
      "kabucom": null,
      "rakuten": null,
      "sbi": null,
      "gmo": null,
      "matsui": null,
      "monex": null
    },
    "taisyaku": "制度信用銘柄",
    "is_taishaku": false,
    "kabuka": 1072,
    "kabusu": 1000,
    "max_gyaku": 8800,
    "gyaku_days": 1,
    "avg5_gyaku": 0.0,
    "haito": null,
    "gl_value": 0,
    "yutai": "【1000株】デジタルギフト15,000円相当",
    "yutai_syubetsu": "ギフトカード",
    "restriction": "",
    "d_kenri": "2月末<br>8月31日",
    "updated": "2026-01-13T09:54:34.674839"
  },
  "3557": {
    "name": "ユナイテッド＆コレクティブ",
    "zaiko": {
      "nikko": null,
      "kabucom": null,
      "rakuten": null,
      "sbi": null,
      "gmo": null,
      "matsui": null,
      "monex": null
    },
    "taisyaku": "制度信用銘柄",
    "is_taishaku": false,
    "kabuka": 1000,
    "kabusu": 100,
    "max_gyaku": 800,
    "gyaku_days": 1,
    "avg5_gyaku": 0.0,
    "haito": null,
    "gl_value": 2000,
    "yutai": "【100株】優待食事券5000円相当",
    "yutai_syubetsu": "買物券",
    "restriction": "",
    "d_kenri": "2月末<br>8月31日",
    "updated": "2026-01-13T09:54:34.674843"
  },
  "3560": {
    "name": "ほぼ日",
    "zaiko": {
      "nikko": null,
      "kabucom": null,
      "rakuten": null,
      "sbi": null,
      "gmo": null,
      "matsui": null,
      "monex": null
    },
    "taisyaku": "制度信用銘柄",
    "is_taishaku": false,
    "kabuka": 3500,
    "kabusu": 100,
    "max_gyaku": 2800,
    "gyaku_days": 1,
    "avg5_gyaku": 0.0,
    "haito": 90,
    "gl_value": 400,
    "yutai": "【100株】自社商品",
    "yutai_syubetsu": "自社商品",
    "restriction": "",
    "d_kenri": "8月31日",
    "updated": "2026-01-13T09:54:34.674847"
  },
  "3562": {
    "name": "Ｎｏ．１",
    "zaiko": {
      "nikko": null,
      "kabucom": null,
      "rakuten": null,
      "sbi": null,
      "gmo": null,
      "matsui": null,
      "monex": null
    },
    "taisyaku": "制度信用銘柄",
    "is_taishaku": false,
    "kabuka": 2522,
    "kabusu": 300,
    "max_gyaku": 6240,
    "gyaku_days": 1,
    "avg5_gyaku": 0.0,
    "haito": null,
    "gl_value": 14250,
    "yutai": "【300株】クオカード15000円相当",
    "yutai_syubetsu": "クオカード",
    "restriction": "",
    "d_kenri": "2月末<br>8月31日",
    "updated": "2026-01-13T09:54:34.674851"
  },
  "3607": {
    "name": "クラウディアホールディングス",
    "zaiko": {
      "nikko": 0,
      "kabucom": null,
      "rakuten": null,
      "sbi": null,
      "gmo": null,
      "matsui": null,
      "monex": null
    },
    "taisyaku": "制度信用銘柄",
    "is_taishaku": false,
    "kabuka": 332,
    "kabusu": 100,
    "max_gyaku": 400,
    "gyaku_days": 1,
    "avg5_gyaku": 0.0,
    "haito": 5,
    "gl_value": 475,
    "yutai": "【100株】クオカード500円相当など",
    "yutai_syubetsu": "クオカード",
    "restriction": "",
    "d_kenri": "8月31日",
    "updated": "2026-01-13T09:54:34.674855"
  },
  "3608": {
    "name": "ＴＳＩホールディングス",
    "zaiko": {
      "nikko": 1600,
      "kabucom": 211200,
      "rakuten": 0,
      "sbi": null,
      "gmo": null,
      "matsui": 2,
      "monex": 1
    },
    "taisyaku": "貸借銘柄",
    "is_taishaku": true,
    "kabuka": 1099,
    "kabusu": 100,
    "max_gyaku": 880,
    "gyaku_days": 1,
    "avg5_gyaku": 0.84,
    "haito": null,
    "gl_value": 10,
    "yutai": "【100株】株主優待券（20%割引）1冊",
    "yutai_syubetsu": "割引券",
    "restriction": "",
    "d_kenri": "2月末日<br>8月31日",
    "updated": "2026-01-13T09:54:34.674859"
  },
  "3612": {
    "name": "ワールド",
    "zaiko": {
      "nikko": 5000,
      "kabucom": 15400,
      "rakuten": 0,
      "sbi": null,
      "gmo": null,
      "matsui": 2,
      "monex": 1
    },
    "taisyaku": "貸借銘柄",
    "is_taishaku": true,
    "kabuka": 3130,
    "kabusu": 600,
    "max_gyaku": 15360,
    "gyaku_days": 1,
    "avg5_gyaku": 1.91,
    "haito": null,
    "gl_value": 2500,
    "yutai": "【600株】株主優待券5000円相当【注：継続保有制限】",
    "yutai_syubetsu": "買物券",
    "restriction": "",
    "d_kenri": "2月末<br>8月31日",
    "updated": "2026-01-13T09:54:34.674863"
  },
  "373A": {
    "name": "リップス",
    "zaiko": {
      "nikko": null,
      "kabucom": null,
      "rakuten": null,
      "sbi": null,
      "gmo": null,
      "matsui": null,
      "monex": null
    },
    "taisyaku": "制度信用銘柄",
    "is_taishaku": false,
    "kabuka": 1839,
    "kabusu": 100,
    "max_gyaku": 1520,
    "gyaku_days": 1,
    "avg5_gyaku": 0.0,
    "haito": 0,
    "gl_value": 0,
    "yutai": "【100株】リップス商品に利用できるオンラインギフト5000円分",
    "yutai_syubetsu": "自社商品",
    "restriction": "",
    "d_kenri": "8月31日",
    "updated": "2026-01-13T09:54:34.674867"
  },
  "3815": {
    "name": "メディア工房",
    "zaiko": {
      "nikko": null,
      "kabucom": null,
      "rakuten": null,
      "sbi": null,
      "gmo": null,
      "matsui": null,
      "monex": null
    },
    "taisyaku": "制度信用銘柄",
    "is_taishaku": false,
    "kabuka": 508,
    "kabusu": 100,
    "max_gyaku": 480,
    "gyaku_days": 1,
    "avg5_gyaku": 0.0,
    "haito": 0,
    "gl_value": 3800,
    "yutai": "【100株】デジタルギフト4000円相当\t",
    "yutai_syubetsu": "ギフトカード",
    "restriction": "",
    "d_kenri": "8月31日",
    "updated": "2026-01-13T09:54:34.674870"
  },
  "3826": {
    "name": "システムインテグレータ",
    "zaiko": {
      "nikko": 0,
      "kabucom": null,
      "rakuten": null,
      "sbi": null,
      "gmo": null,
      "matsui": null,
      "monex": 1
    },
    "taisyaku": "貸借銘柄",
    "is_taishaku": true,
    "kabuka": 480,
    "kabusu": 200,
    "max_gyaku": 800,
    "gyaku_days": 1,
    "avg5_gyaku": 0.17,
    "haito": null,
    "gl_value": 250,
    "yutai": "【200株】新潟県産コシヒカリ【注：継続保有制限】",
    "yutai_syubetsu": "食べ物",
    "restriction": "",
    "d_kenri": "8月31日",
    "updated": "2026-01-13T09:54:34.674874"
  },
  "3967": {
    "name": "エルテス",
    "zaiko": {
      "nikko": null,
      "kabucom": null,
      "rakuten": null,
      "sbi": null,
      "gmo": null,
      "matsui": null,
      "monex": 1
    },
    "taisyaku": "制度信用銘柄",
    "is_taishaku": false,
    "kabuka": 686,
    "kabusu": 800,
    "max_gyaku": 4480,
    "gyaku_days": 1,
    "avg5_gyaku": 0.0,
    "haito": null,
    "gl_value": 9500,
    "yutai": "【800株】\tデジタルギフト5000円相当",
    "yutai_syubetsu": "ギフトカード",
    "restriction": "",
    "d_kenri": "2月末日<br>8月31日",
    "updated": "2026-01-13T09:54:34.674878"
  },
  "3987": {
    "name": "エコモット",
    "zaiko": {
      "nikko": null,
      "kabucom": null,
      "rakuten": null,
      "sbi": null,
      "gmo": null,
      "matsui": null,
      "monex": null
    },
    "taisyaku": "貸借銘柄",
    "is_taishaku": true,
    "kabuka": 510,
    "kabusu": 100,
    "max_gyaku": 480,
    "gyaku_days": 1,
    "avg5_gyaku": 0.0,
    "haito": 0,
    "gl_value": 0,
    "yutai": "【100株】オンラインショップで利用できるギフトカード4,000円分",
    "yutai_syubetsu": "カタログギフト",
    "restriction": "停止",
    "d_kenri": "8月31日",
    "updated": "2026-01-13T09:54:34.674881"
  },
  "4015": {
    "name": "ペイクラウドホールディングス",
    "zaiko": {
      "nikko": null,
      "kabucom": null,
      "rakuten": null,
      "sbi": null,
      "gmo": null,
      "matsui": null,
      "monex": 0
    },
    "taisyaku": "制度信用銘柄",
    "is_taishaku": false,
    "kabuka": 542,
    "kabusu": 300,
    "max_gyaku": 1440,
    "gyaku_days": 1,
    "avg5_gyaku": 0.0,
    "haito": 0,
    "gl_value": 2000,
    "yutai": "【300株】デジタルギフト5000円相当",
    "yutai_syubetsu": "自社商品",
    "restriction": "",
    "d_kenri": "8月31日",
    "updated": "2026-01-13T09:54:34.674885"
  },
  "428A": {
    "name": "サイプレス・ホールディングス",
    "zaiko": {
      "nikko": null,
      "kabucom": null,
      "rakuten": null,
      "sbi": null,
      "gmo": null,
      "matsui": null,
      "monex": null
    },
    "taisyaku": "制度信用銘柄",
    "is_taishaku": false,
    "kabuka": 831,
    "kabusu": 100,
    "max_gyaku": 720,
    "gyaku_days": 1,
    "avg5_gyaku": 0.0,
    "haito": 10,
    "gl_value": 0,
    "yutai": "【100株】電子優待券 1,000円相当",
    "yutai_syubetsu": "買物券",
    "restriction": "",
    "d_kenri": "2月末<br>8月31日",
    "updated": "2026-01-13T09:54:34.674889"
  },
  "4343": {
    "name": "イオンファンタジー",
    "zaiko": {
      "nikko": 0,
      "kabucom": 0,
      "rakuten": 0,
      "sbi": null,
      "gmo": null,
      "matsui": null,
      "monex": 1
    },
    "taisyaku": "貸借銘柄",
    "is_taishaku": true,
    "kabuka": 2981,
    "kabusu": 100,
    "max_gyaku": 2400,
    "gyaku_days": 1,
    "avg5_gyaku": 3.445,
    "haito": null,
    "gl_value": 900,
    "yutai": "【100株】買物券 2000円相当",
    "yutai_syubetsu": "買物券",
    "restriction": "",
    "d_kenri": "2月末日<br>8月31日",
    "updated": "2026-01-13T09:54:34.674893"
  },
  "4397": {
    "name": "チームスピリット",
    "zaiko": {
      "nikko": null,
      "kabucom": null,
      "rakuten": null,
      "sbi": null,
      "gmo": null,
      "matsui": null,
      "monex": 1
    },
    "taisyaku": "制度信用銘柄",
    "is_taishaku": false,
    "kabuka": 521,
    "kabusu": 1000,
    "max_gyaku": 4800,
    "gyaku_days": 1,
    "avg5_gyaku": 0.0,
    "haito": 0,
    "gl_value": 0,
    "yutai": "【1000株】【2025倍額】プレミアム優待クラブ3000ポイント",
    "yutai_syubetsu": "プレミアム優待クラブ",
    "restriction": "",
    "d_kenri": "2月末<br>8月31日",
    "updated": "2026-01-13T09:54:34.674897"
  },
  "4433": {
    "name": "ヒト・コミュニケーションズ・ホールディン",
    "zaiko": {
      "nikko": 1600,
      "kabucom": null,
      "rakuten": null,
      "sbi": null,
      "gmo": null,
      "matsui": null,
      "monex": null
    },
    "taisyaku": "制度信用銘柄",
    "is_taishaku": false,
    "kabuka": 0,
    "kabusu": 100,
    "max_gyaku": 400,
    "gyaku_days": 1,
    "avg5_gyaku": 0.0,
    "haito": null,
    "gl_value": 970,
    "yutai": "【100株】ギフトカード1000円相当",
    "yutai_syubetsu": "ギフトカード",
    "restriction": "",
    "d_kenri": "8月31日",
    "updated": "2026-01-13T09:54:34.674905"
  },
  "4668": {
    "name": "明光ネットワークジャパン",
    "zaiko": {
      "nikko": 2400,
      "kabucom": null,
      "rakuten": null,
      "sbi": null,
      "gmo": null,
      "matsui": null,
      "monex": 1
    },
    "taisyaku": "貸借銘柄",
    "is_taishaku": true,
    "kabuka": 729,
    "kabusu": 100,
    "max_gyaku": 640,
    "gyaku_days": 1,
    "avg5_gyaku": 6.06,
    "haito": 14,
    "gl_value": 475,
    "yutai": "【100株】クオカード 500円相当",
    "yutai_syubetsu": "クオカード",
    "restriction": "",
    "d_kenri": "8月31日",
    "updated": "2026-01-13T09:54:34.674910"
  },
  "5580": {
    "name": "プロディライト",
    "zaiko": {
      "nikko": null,
      "kabucom": null,
      "rakuten": null,
      "sbi": null,
      "gmo": null,
      "matsui": null,
      "monex": null
    },
    "taisyaku": "制度信用銘柄",
    "is_taishaku": false,
    "kabuka": 1679,
    "kabusu": 400,
    "max_gyaku": 5440,
    "gyaku_days": 1,
    "avg5_gyaku": 0.0,
    "haito": 0,
    "gl_value": 0,
    "yutai": "【400株】【2026より継続保有制限】デジタルギフト15000円相当",
    "yutai_syubetsu": "ギフトカード",
    "restriction": "",
    "d_kenri": "8月31日",
    "updated": "2026-01-13T09:54:34.674914"
  },
  "5982": {
    "name": "マルゼン",
    "zaiko": {
      "nikko": null,
      "kabucom": null,
      "rakuten": null,
      "sbi": null,
      "gmo": null,
      "matsui": null,
      "monex": 1
    },
    "taisyaku": "制度信用銘柄",
    "is_taishaku": false,
    "kabuka": 3750,
    "kabusu": 300,
    "max_gyaku": 9120,
    "gyaku_days": 1,
    "avg5_gyaku": 0.0,
    "haito": null,
    "gl_value": 950,
    "yutai": "【300株】クオカード1000円相当",
    "yutai_syubetsu": "クオカード",
    "restriction": "",
    "d_kenri": "2月末日<br>8月31日",
    "updated": "2026-01-13T09:54:34.674918"
  },
  "6025": {
    "name": "日本ＰＣサービス",
    "zaiko": {
      "nikko": null,
      "kabucom": null,
      "rakuten": null,
      "sbi": null,
      "gmo": null,
      "matsui": null,
      "monex": null
    },
    "taisyaku": "",
    "is_taishaku": false,
    "kabuka": 0,
    "kabusu": 500,
    "max_gyaku": 2000,
    "gyaku_days": 1,
    "avg5_gyaku": 0.0,
    "haito": 0,
    "gl_value": 100,
    "yutai": "【500株】株主優待券 5000円相当",
    "yutai_syubetsu": "自社サービス",
    "restriction": "",
    "d_kenri": "8月31日",
    "updated": "2026-01-13T09:54:34.674921"
  },
  "6264": {
    "name": "マルマエ",
    "zaiko": {
      "nikko": 0,
      "kabucom": null,
      "rakuten": null,
      "sbi": null,
      "gmo": null,
      "matsui": null,
      "monex": 1
    },
    "taisyaku": "貸借銘柄",
    "is_taishaku": true,
    "kabuka": 2258,
    "kabusu": 100,
    "max_gyaku": 1840,
    "gyaku_days": 1,
    "avg5_gyaku": 0.02,
    "haito": 28,
    "gl_value": 950,
    "yutai": "【100株】クオカード1000円相当【注：継続保有制限】",
    "yutai_syubetsu": "クオカード",
    "restriction": "",
    "d_kenri": "8月31日",
    "updated": "2026-01-13T09:54:34.674925"
  },
  "6289": {
    "name": "技研製作所",
    "zaiko": {
      "nikko": 6400,
      "kabucom": null,
      "rakuten": 0,
      "sbi": null,
      "gmo": null,
      "matsui": null,
      "monex": null
    },
    "taisyaku": "貸借銘柄",
    "is_taishaku": true,
    "kabuka": 2024,
    "kabusu": 300,
    "max_gyaku": 5040,
    "gyaku_days": 1,
    "avg5_gyaku": 0.575,
    "haito": 27,
    "gl_value": 0,
    "yutai": "【300株】プレミアム優待クラブ 2000ポイント",
    "yutai_syubetsu": "プレミアム優待クラブ",
    "restriction": "",
    "d_kenri": "2月末<br>8月31日",
    "updated": "2026-01-13T09:54:34.674930"
  },
  "6543": {
    "name": "日宣",
    "zaiko": {
      "nikko": null,
      "kabucom": null,
      "rakuten": null,
      "sbi": null,
      "gmo": null,
      "matsui": null,
      "monex": null
    },
    "taisyaku": "制度信用銘柄",
    "is_taishaku": false,
    "kabuka": 1284,
    "kabusu": 300,
    "max_gyaku": 3120,
    "gyaku_days": 1,
    "avg5_gyaku": 0.0,
    "haito": null,
    "gl_value": 0,
    "yutai": "【300株】【2026より継続保有制限】クオカード5000円相当",
    "yutai_syubetsu": "クオカード",
    "restriction": "",
    "d_kenri": "2月末<br>8月31日",
    "updated": "2026-01-13T09:54:34.674933"
  },
  "6578": {
    "name": "コレックホールディングス",
    "zaiko": {
      "nikko": null,
      "kabucom": null,
      "rakuten": null,
      "sbi": null,
      "gmo": null,
      "matsui": null,
      "monex": null
    },
    "taisyaku": "制度信用銘柄",
    "is_taishaku": false,
    "kabuka": 417,
    "kabusu": 100,
    "max_gyaku": 400,
    "gyaku_days": 1,
    "avg5_gyaku": 0.0,
    "haito": null,
    "gl_value": 0,
    "yutai": "【100株】クオカード1000円相当",
    "yutai_syubetsu": "クオカード",
    "restriction": "",
    "d_kenri": "2月末<br>8月31日",
    "updated": "2026-01-13T09:54:34.674937"
  },
  "7035": {
    "name": "ａｎｄ　ｆａｃｔｏｒｙ",
    "zaiko": {
      "nikko": null,
      "kabucom": null,
      "rakuten": null,
      "sbi": null,
      "gmo": null,
      "matsui": null,
      "monex": null
    },
    "taisyaku": "貸借銘柄",
    "is_taishaku": true,
    "kabuka": 219,
    "kabusu": 1000,
    "max_gyaku": 4000,
    "gyaku_days": 1,
    "avg5_gyaku": 1.53,
    "haito": 0,
    "gl_value": 3000,
    "yutai": "【1000株】プレミアム優待クラブ5,000ポイント",
    "yutai_syubetsu": "プレミアム優待クラブ",
    "restriction": "注意",
    "d_kenri": "8月31日",
    "updated": "2026-01-13T09:54:34.674941"
  },
  "7049": {
    "name": "識学",
    "zaiko": {
      "nikko": null,
      "kabucom": null,
      "rakuten": null,
      "sbi": null,
      "gmo": null,
      "matsui": null,
      "monex": null
    },
    "taisyaku": "貸借銘柄",
    "is_taishaku": true,
    "kabuka": 993,
    "kabusu": 200,
    "max_gyaku": 1600,
    "gyaku_days": 1,
    "avg5_gyaku": 8.625,
    "haito": null,
    "gl_value": 4750,
    "yutai": "【200株】クオカード5000円相当",
    "yutai_syubetsu": "クオカード",
    "restriction": "",
    "d_kenri": "2月末<br>8月31日",
    "updated": "2026-01-13T09:54:34.674945"
  },
  "7077": {
    "name": "ＡＬｉＮＫインターネット",
    "zaiko": {
      "nikko": null,
      "kabucom": null,
      "rakuten": null,
      "sbi": null,
      "gmo": null,
      "matsui": null,
      "monex": null
    },
    "taisyaku": "制度信用銘柄",
    "is_taishaku": false,
    "kabuka": 1066,
    "kabusu": 100,
    "max_gyaku": 880,
    "gyaku_days": 1,
    "avg5_gyaku": 0.0,
    "haito": null,
    "gl_value": 950,
    "yutai": "【100株】クオカード1000円相当",
    "yutai_syubetsu": "クオカード",
    "restriction": "",
    "d_kenri": "2月末<br>8月31日",
    "updated": "2026-01-13T09:54:34.674948"
  },
  "7085": {
    "name": "カーブスホールディングス",
    "zaiko": {
      "nikko": 1500,
      "kabucom": 7700,
      "rakuten": null,
      "sbi": null,
      "gmo": 0,
      "matsui": 2,
      "monex": 1
    },
    "taisyaku": "貸借銘柄",
    "is_taishaku": true,
    "kabuka": 799,
    "kabusu": 100,
    "max_gyaku": 640,
    "gyaku_days": 1,
    "avg5_gyaku": 0.6,
    "haito": 15,
    "gl_value": 475,
    "yutai": "【100株】クオカード 500円相当",
    "yutai_syubetsu": "クオカード",
    "restriction": "",
    "d_kenri": "8月31日",
    "updated": "2026-01-13T09:54:34.674953"
  },
  "7219": {
    "name": "エッチ・ケー・エス",
    "zaiko": {
      "nikko": null,
      "kabucom": null,
      "rakuten": null,
      "sbi": null,
      "gmo": null,
      "matsui": null,
      "monex": null
    },
    "taisyaku": "制度信用銘柄",
    "is_taishaku": false,
    "kabuka": 2242,
    "kabusu": 100,
    "max_gyaku": 1840,
    "gyaku_days": 1,
    "avg5_gyaku": 0.0,
    "haito": 65,
    "gl_value": 0,
    "yutai": "【100株】クオカード1000円相当",
    "yutai_syubetsu": "クオカード",
    "restriction": "",
    "d_kenri": "8月31日",
    "updated": "2026-01-13T09:54:34.674956"
  },
  "7352": {
    "name": "ＴＷＯＳＴＯＮＥ＆Ｓｏｎｓ",
    "zaiko": {
      "nikko": null,
      "kabucom": null,
      "rakuten": null,
      "sbi": null,
      "gmo": null,
      "matsui": null,
      "monex": null
    },
    "taisyaku": "制度信用銘柄",
    "is_taishaku": false,
    "kabuka": 882,
    "kabusu": 100,
    "max_gyaku": 720,
    "gyaku_days": 1,
    "avg5_gyaku": 0.0,
    "haito": null,
    "gl_value": 0,
    "yutai": "【100株】自社サービス利用時の特典",
    "yutai_syubetsu": "自社サービス",
    "restriction": "",
    "d_kenri": "8月31日",
    "updated": "2026-01-13T09:54:34.674961"
  },
  "7357": {
    "name": "ジオコード",
    "zaiko": {
      "nikko": null,
      "kabucom": null,
      "rakuten": null,
      "sbi": null,
      "gmo": null,
      "matsui": null,
      "monex": null
    },
    "taisyaku": "制度信用銘柄",
    "is_taishaku": false,
    "kabuka": 1469,
    "kabusu": 200,
    "max_gyaku": 2400,
    "gyaku_days": 1,
    "avg5_gyaku": 0.0,
    "haito": null,
    "gl_value": 0,
    "yutai": "【200株】デジタルギフト5000円",
    "yutai_syubetsu": "ギフトカード",
    "restriction": "",
    "d_kenri": "2月末<br>8月31日",
    "updated": "2026-01-13T09:54:34.674965"
  },
  "7450": {
    "name": "サンデー",
    "zaiko": {
      "nikko": null,
      "kabucom": null,
      "rakuten": null,
      "sbi": null,
      "gmo": null,
      "matsui": null,
      "monex": null
    },
    "taisyaku": "制度信用銘柄",
    "is_taishaku": false,
    "kabuka": 0,
    "kabusu": 100,
    "max_gyaku": 400,
    "gyaku_days": 1,
    "avg5_gyaku": 0.0,
    "haito": null,
    "gl_value": 600,
    "yutai": "【100株】東北地方特産品1500円相当",
    "yutai_syubetsu": "自社商品",
    "restriction": "",
    "d_kenri": "8月31日",
    "updated": "2026-01-13T09:54:34.674968"
  },
  "7453": {
    "name": "良品計画",
    "zaiko": {
      "nikko": 1000,
      "kabucom": 62400,
      "rakuten": 0,
      "sbi": 2,
      "gmo": null,
      "matsui": 2,
      "monex": 2
    },
    "taisyaku": "貸借銘柄",
    "is_taishaku": true,
    "kabuka": 2825,
    "kabusu": 100,
    "max_gyaku": 2320,
    "gyaku_days": 1,
    "avg5_gyaku": 0.844444,
    "haito": 14,
    "gl_value": 100,
    "yutai": "【100株】優待カード（7%割引）",
    "yutai_syubetsu": "割引券",
    "restriction": "",
    "d_kenri": "2月末<br>8月31日",
    "updated": "2026-01-13T09:54:34.674973"
  },
  "7485": {
    "name": "岡谷鋼機",
    "zaiko": {
      "nikko": null,
      "kabucom": null,
      "rakuten": null,
      "sbi": null,
      "gmo": null,
      "matsui": null,
      "monex": null
    },
    "taisyaku": "",
    "is_taishaku": false,
    "kabuka": 0,
    "kabusu": 400,
    "max_gyaku": 1600,
    "gyaku_days": 1,
    "avg5_gyaku": 0.0,
    "haito": null,
    "gl_value": 1250,
    "yutai": "【400株】愛知米ミネアサヒ5kg",
    "yutai_syubetsu": "食べ物",
    "restriction": "停止",
    "d_kenri": "2月末<br>8月31日",
    "updated": "2026-01-13T09:54:34.674976"
  },
  "7513": {
    "name": "コジマ",
    "zaiko": {
      "nikko": 6800,
      "kabucom": null,
      "rakuten": 0,
      "sbi": null,
      "gmo": null,
      "matsui": null,
      "monex": 1
    },
    "taisyaku": "貸借銘柄",
    "is_taishaku": true,
    "kabuka": 1179,
    "kabusu": 100,
    "max_gyaku": 960,
    "gyaku_days": 1,
    "avg5_gyaku": 1.63,
    "haito": 22,
    "gl_value": 900,
    "yutai": "【100株】買物券 1000円相当",
    "yutai_syubetsu": "買物券",
    "restriction": "",
    "d_kenri": "2月末<br>8月31日",
    "updated": "2026-01-13T09:54:34.674980"
  },
  "7514": {
    "name": "ヒマラヤ",
    "zaiko": {
      "nikko": 0,
      "kabucom": null,
      "rakuten": null,
      "sbi": null,
      "gmo": null,
      "matsui": null,
      "monex": 1
    },
    "taisyaku": "制度信用銘柄",
    "is_taishaku": false,
    "kabuka": 0,
    "kabusu": 100,
    "max_gyaku": 400,
    "gyaku_days": 1,
    "avg5_gyaku": 0.0,
    "haito": 13,
    "gl_value": 700,
    "yutai": "【100株】ご優待割引券1000円相当 もしくは ヒマラヤポイント1000ポイント",
    "yutai_syubetsu": "買物券",
    "restriction": "",
    "d_kenri": "2月末日<br>8月31日",
    "updated": "2026-01-13T09:54:34.674984"
  },
  "7603": {
    "name": "ジーイエット",
    "zaiko": {
      "nikko": null,
      "kabucom": null,
      "rakuten": null,
      "sbi": null,
      "gmo": null,
      "matsui": null,
      "monex": null
    },
    "taisyaku": "貸借銘柄",
    "is_taishaku": true,
    "kabuka": 165,
    "kabusu": 100,
    "max_gyaku": 400,
    "gyaku_days": 1,
    "avg5_gyaku": 9.75,
    "haito": null,
    "gl_value": 500,
    "yutai": "【100株】優待券 1000円相当など",
    "yutai_syubetsu": "買物券",
    "restriction": "停止",
    "d_kenri": "2月末日<br>8月31日",
    "updated": "2026-01-13T09:54:34.674988"
  },
  "7607": {
    "name": "進和",
    "zaiko": {
      "nikko": 900,
      "kabucom": 1700,
      "rakuten": null,
      "sbi": null,
      "gmo": null,
      "matsui": 2,
      "monex": 1
    },
    "taisyaku": "貸借銘柄",
    "is_taishaku": true,
    "kabuka": 3160,
    "kabusu": 100,
    "max_gyaku": 2560,
    "gyaku_days": 1,
    "avg5_gyaku": 5.3,
    "haito": 62,
    "gl_value": 800,
    "yutai": "【100株】お米券2kg【注：継続保有制限】",
    "yutai_syubetsu": "お米券",
    "restriction": "",
    "d_kenri": "8月31日",
    "updated": "2026-01-13T09:54:34.674992"
  },
  "7611": {
    "name": "ハイデイ日高",
    "zaiko": {
      "nikko": 3800,
      "kabucom": null,
      "rakuten": 0,
      "sbi": null,
      "gmo": 2,
      "matsui": null,
      "monex": 1
    },
    "taisyaku": "貸借銘柄",
    "is_taishaku": true,
    "kabuka": 3340,
    "kabusu": 100,
    "max_gyaku": 2720,
    "gyaku_days": 1,
    "avg5_gyaku": 5.75,
    "haito": null,
    "gl_value": 800,
    "yutai": "【100株】買物券 1000円相当",
    "yutai_syubetsu": "買物券",
    "restriction": "",
    "d_kenri": "2月末日<br>8月31日",
    "updated": "2026-01-13T09:54:34.674997"
  },
  "7630": {
    "name": "壱番屋",
    "zaiko": {
      "nikko": 4100,
      "kabucom": 2800,
      "rakuten": 0,
      "sbi": null,
      "gmo": null,
      "matsui": null,
      "monex": null
    },
    "taisyaku": "貸借銘柄",
    "is_taishaku": true,
    "kabuka": 919,
    "kabusu": 100,
    "max_gyaku": 800,
    "gyaku_days": 1,
    "avg5_gyaku": 5.54,
    "haito": null,
    "gl_value": 860,
    "yutai": "【100株】買物券 1000円相当",
    "yutai_syubetsu": "買物券",
    "restriction": "",
    "d_kenri": "2月末日<br>8月31日",
    "updated": "2026-01-13T09:54:34.675001"
  },
  "7730": {
    "name": "マニー",
    "zaiko": {
      "nikko": 900,
      "kabucom": 235600,
      "rakuten": null,
      "sbi": null,
      "gmo": null,
      "matsui": 2,
      "monex": 1
    },
    "taisyaku": "貸借銘柄",
    "is_taishaku": true,
    "kabuka": 1478,
    "kabusu": 300,
    "max_gyaku": 3600,
    "gyaku_days": 1,
    "avg5_gyaku": 1.31,
    "haito": 24,
    "gl_value": 2850,
    "yutai": "【300株】クオカード3000円相当【注：継続保有制限】",
    "yutai_syubetsu": "クオカード",
    "restriction": "",
    "d_kenri": "8月31日",
    "updated": "2026-01-13T09:54:34.675006"
  },
  "7805": {
    "name": "プリントネット",
    "zaiko": {
      "nikko": null,
      "kabucom": null,
      "rakuten": null,
      "sbi": null,
      "gmo": null,
      "matsui": null,
      "monex": null
    },
    "taisyaku": "貸借銘柄",
    "is_taishaku": true,
    "kabuka": 689,
    "kabusu": 100,
    "max_gyaku": 560,
    "gyaku_days": 1,
    "avg5_gyaku": 20.32,
    "haito": 13,
    "gl_value": 475,
    "yutai": "【100株】デジタルギフト500円",
    "yutai_syubetsu": "ギフトカード",
    "restriction": "",
    "d_kenri": "8月31日",
    "updated": "2026-01-13T09:54:34.675010"
  },
  "7818": {
    "name": "トランザクション",
    "zaiko": {
      "nikko": 4900,
      "kabucom": null,
      "rakuten": 0,
      "sbi": null,
      "gmo": null,
      "matsui": null,
      "monex": 1
    },
    "taisyaku": "貸借銘柄",
    "is_taishaku": true,
    "kabuka": 1135,
    "kabusu": 500,
    "max_gyaku": 4800,
    "gyaku_days": 1,
    "avg5_gyaku": 0.9,
    "haito": 30,
    "gl_value": 2000,
    "yutai": "【500株】自社製品",
    "yutai_syubetsu": "自社商品",
    "restriction": "",
    "d_kenri": "2月末日<br>8月31日",
    "updated": "2026-01-13T09:54:34.675014"
  },
  "7829": {
    "name": "サマンサタバサジャパンリミテッド",
    "zaiko": {
      "nikko": null,
      "kabucom": null,
      "rakuten": null,
      "sbi": null,
      "gmo": null,
      "matsui": null,
      "monex": null
    },
    "taisyaku": "制度信用銘柄",
    "is_taishaku": false,
    "kabuka": 0,
    "kabusu": 100,
    "max_gyaku": 400,
    "gyaku_days": 1,
    "avg5_gyaku": 0.0,
    "haito": null,
    "gl_value": 0,
    "yutai": "【100株】優待割引券（15%割引）2枚",
    "yutai_syubetsu": "割引券",
    "restriction": "",
    "d_kenri": "2月末日<br>8月末日",
    "updated": "2026-01-13T09:54:34.675018"
  },
  "7928": {
    "name": "旭化学工業",
    "zaiko": {
      "nikko": null,
      "kabucom": null,
      "rakuten": null,
      "sbi": null,
      "gmo": null,
      "matsui": null,
      "monex": null
    },
    "taisyaku": "制度信用銘柄",
    "is_taishaku": false,
    "kabuka": 592,
    "kabusu": 100,
    "max_gyaku": 480,
    "gyaku_days": 1,
    "avg5_gyaku": 0.0,
    "haito": 5,
    "gl_value": 950,
    "yutai": "【100株】クオカード1000円相当",
    "yutai_syubetsu": "クオカード",
    "restriction": "",
    "d_kenri": "8月31日",
    "updated": "2026-01-13T09:54:34.675022"
  },
  "8011": {
    "name": "三陽商会",
    "zaiko": {
      "nikko": 0,
      "kabucom": null,
      "rakuten": 100,
      "sbi": null,
      "gmo": null,
      "matsui": 2,
      "monex": 1
    },
    "taisyaku": "貸借銘柄",
    "is_taishaku": true,
    "kabuka": 4075,
    "kabusu": 600,
    "max_gyaku": 19680,
    "gyaku_days": 1,
    "avg5_gyaku": 3.46,
    "haito": null,
    "gl_value": 0,
    "yutai": "【600株】【分割後】SMSポイント2500P 及び 優待セール入場券",
    "yutai_syubetsu": "買物券",
    "restriction": "",
    "d_kenri": "2月末日<br>8月31日",
    "updated": "2026-01-13T09:54:34.675026"
  },
  "8127": {
    "name": "ヤマトインターナショナル",
    "zaiko": {
      "nikko": 0,
      "kabucom": null,
      "rakuten": null,
      "sbi": null,
      "gmo": null,
      "matsui": null,
      "monex": null
    },
    "taisyaku": "貸借銘柄",
    "is_taishaku": true,
    "kabuka": 605,
    "kabusu": 300,
    "max_gyaku": 1680,
    "gyaku_days": 1,
    "avg5_gyaku": 4.61,
    "haito": 8,
    "gl_value": 400,
    "yutai": "【300株】自社商品 1000円相当",
    "yutai_syubetsu": "自社商品",
    "restriction": "注意",
    "d_kenri": "8月31日",
    "updated": "2026-01-13T09:54:34.675030"
  },
  "8167": {
    "name": "リテールパートナーズ",
    "zaiko": {
      "nikko": 4100,
      "kabucom": null,
      "rakuten": null,
      "sbi": null,
      "gmo": null,
      "matsui": null,
      "monex": 1
    },
    "taisyaku": "貸借銘柄",
    "is_taishaku": true,
    "kabuka": 1359,
    "kabusu": 100,
    "max_gyaku": 1120,
    "gyaku_days": 1,
    "avg5_gyaku": 4.485,
    "haito": null,
    "gl_value": 970,
    "yutai": "【100株】ＪＣＢギフトカードなど 1000円相当",
    "yutai_syubetsu": "ギフトカード",
    "restriction": "",
    "d_kenri": "2月末日<br>8月31日",
    "updated": "2026-01-13T09:54:34.675034"
  },
  "8181": {
    "name": "東天紅",
    "zaiko": {
      "nikko": 0,
      "kabucom": null,
      "rakuten": null,
      "sbi": null,
      "gmo": null,
      "matsui": null,
      "monex": 1
    },
    "taisyaku": "制度信用銘柄",
    "is_taishaku": false,
    "kabuka": 1130,
    "kabusu": 100,
    "max_gyaku": 960,
    "gyaku_days": 1,
    "avg5_gyaku": 0.0,
    "haito": null,
    "gl_value": 40,
    "yutai": "【100株】割引券20% 4枚",
    "yutai_syubetsu": "割引券",
    "restriction": "",
    "d_kenri": "2月末日<br>8月31日",
    "updated": "2026-01-13T09:54:34.675038"
  },
  "8184": {
    "name": "null",
    "zaiko": {
      "nikko": null,
      "kabucom": null,
      "rakuten": null,
      "sbi": null,
      "gmo": null,
      "matsui": null,
      "monex": null
    },
    "taisyaku": "",
    "is_taishaku": false,
    "kabuka": 0,
    "kabusu": 1000,
    "max_gyaku": 4000,
    "gyaku_days": 1,
    "avg5_gyaku": 0.0,
    "haito": null,
    "gl_value": 800,
    "yutai": "【1000株】割引券10% 10枚",
    "yutai_syubetsu": "割引券",
    "restriction": "",
    "d_kenri": "8月31日",
    "updated": "2026-01-13T09:54:34.675042"
  },
  "8185": {
    "name": "チヨダ",
    "zaiko": {
      "nikko": 1300,
      "kabucom": 2800,
      "rakuten": 0,
      "sbi": null,
      "gmo": null,
      "matsui": null,
      "monex": 1
    },
    "taisyaku": "貸借銘柄",
    "is_taishaku": true,
    "kabuka": 1119,
    "kabusu": 100,
    "max_gyaku": 960,
    "gyaku_days": 1,
    "avg5_gyaku": 0.615,
    "haito": null,
    "gl_value": 5,
    "yutai": "【100株】割引券20% 5枚",
    "yutai_syubetsu": "割引券",
    "restriction": "",
    "d_kenri": "2月末日<br>8月31日",
    "updated": "2026-01-13T09:54:34.675046"
  },
  "8200": {
    "name": "リンガーハット",
    "zaiko": {
      "nikko": 14800,
      "kabucom": null,
      "rakuten": 0,
      "sbi": null,
      "gmo": null,
      "matsui": null,
      "monex": null
    },
    "taisyaku": "貸借銘柄",
    "is_taishaku": true,
    "kabuka": 2311,
    "kabusu": 100,
    "max_gyaku": 1920,
    "gyaku_days": 1,
    "avg5_gyaku": 7.175,
    "haito": null,
    "gl_value": 1230,
    "yutai": "【100株】株主優待ポイント1650円相当",
    "yutai_syubetsu": "買物券",
    "restriction": "",
    "d_kenri": "2月末日<br>8月31日",
    "updated": "2026-01-13T09:54:34.675050"
  },
  "8233": {
    "name": "高島屋",
    "zaiko": {
      "nikko": 900,
      "kabucom": 6500,
      "rakuten": 0,
      "sbi": 2,
      "gmo": null,
      "matsui": 2,
      "monex": 2
    },
    "taisyaku": "貸借銘柄",
    "is_taishaku": true,
    "kabuka": 1858,
    "kabusu": 100,
    "max_gyaku": 1520,
    "gyaku_days": 1,
    "avg5_gyaku": 0.88,
    "haito": null,
    "gl_value": 1500,
    "yutai": "【100株】割引カード10% (限度額15万円)",
    "yutai_syubetsu": "割引券",
    "restriction": "",
    "d_kenri": "2月末日<br>8月31日",
    "updated": "2026-01-13T09:54:34.675054"
  },
  "8237": {
    "name": "松屋",
    "zaiko": {
      "nikko": 1800,
      "kabucom": 3200,
      "rakuten": 0,
      "sbi": null,
      "gmo": null,
      "matsui": 2,
      "monex": 1
    },
    "taisyaku": "貸借銘柄",
    "is_taishaku": true,
    "kabuka": 1792,
    "kabusu": 100,
    "max_gyaku": 1440,
    "gyaku_days": 1,
    "avg5_gyaku": 0.365,
    "haito": null,
    "gl_value": 250,
    "yutai": "【100株】買物優待カード（10%割引）",
    "yutai_syubetsu": "割引券",
    "restriction": "",
    "d_kenri": "2月末日<br>8月31日",
    "updated": "2026-01-13T09:54:34.675058"
  },
  "8244": {
    "name": "近鉄百貨店",
    "zaiko": {
      "nikko": 1900,
      "kabucom": null,
      "rakuten": null,
      "sbi": null,
      "gmo": null,
      "matsui": null,
      "monex": 1
    },
    "taisyaku": "貸借銘柄",
    "is_taishaku": true,
    "kabuka": 1848,
    "kabusu": 100,
    "max_gyaku": 1520,
    "gyaku_days": 1,
    "avg5_gyaku": 0.5,
    "haito": null,
    "gl_value": 500,
    "yutai": "【100株】株主様お買物優待カード(10%割引：店舗上限額300万円、ネット上限額30万円)など",
    "yutai_syubetsu": "割引券",
    "restriction": "",
    "d_kenri": "2月末日<br>8月31日",
    "updated": "2026-01-13T09:54:34.675062"
  },
  "8247": {
    "name": "大和",
    "zaiko": {
      "nikko": null,
      "kabucom": null,
      "rakuten": null,
      "sbi": null,
      "gmo": null,
      "matsui": null,
      "monex": 1
    },
    "taisyaku": "制度信用銘柄",
    "is_taishaku": false,
    "kabuka": 0,
    "kabusu": 100,
    "max_gyaku": 400,
    "gyaku_days": 1,
    "avg5_gyaku": 0.0,
    "haito": null,
    "gl_value": 10,
    "yutai": "【100株】買物優待カード（10%割引）",
    "yutai_syubetsu": "割引券",
    "restriction": "",
    "d_kenri": "2月末日<br>8月31日",
    "updated": "2026-01-13T09:54:34.675066"
  },
  "8254": {
    "name": "さいか屋",
    "zaiko": {
      "nikko": null,
      "kabucom": null,
      "rakuten": null,
      "sbi": null,
      "gmo": null,
      "matsui": null,
      "monex": null
    },
    "taisyaku": "貸借銘柄",
    "is_taishaku": true,
    "kabuka": 418,
    "kabusu": 100,
    "max_gyaku": 400,
    "gyaku_days": 1,
    "avg5_gyaku": 0.0,
    "haito": null,
    "gl_value": 0,
    "yutai": "【100株】株主お買物優待券(10％割引)15枚 及び AFC割引券2,500円券×2枚など",
    "yutai_syubetsu": "割引券",
    "restriction": "停止",
    "d_kenri": "2月末日<br>8月31日",
    "updated": "2026-01-13T09:54:34.675069"
  },
  "8260": {
    "name": "井筒屋",
    "zaiko": {
      "nikko": 0,
      "kabucom": null,
      "rakuten": null,
      "sbi": null,
      "gmo": null,
      "matsui": null,
      "monex": 1
    },
    "taisyaku": "貸借銘柄",
    "is_taishaku": true,
    "kabuka": 434,
    "kabusu": 100,
    "max_gyaku": 400,
    "gyaku_days": 1,
    "avg5_gyaku": 0.0,
    "haito": null,
    "gl_value": 2,
    "yutai": "【100株】お買物優待券(7%割引券)",
    "yutai_syubetsu": "割引券",
    "restriction": "",
    "d_kenri": "2月末日<br>8月31日",
    "updated": "2026-01-13T09:54:34.675073"
  },
  "8267": {
    "name": "イオン",
    "zaiko": {
      "nikko": 2700,
      "kabucom": 312200,
      "rakuten": 35300,
      "sbi": 1,
      "gmo": null,
      "matsui": 2,
      "monex": 2
    },
    "taisyaku": "貸借銘柄",
    "is_taishaku": true,
    "kabuka": 2182,
    "kabusu": 100,
    "max_gyaku": 1760,
    "gyaku_days": 1,
    "avg5_gyaku": 2.05,
    "haito": null,
    "gl_value": 100,
    "yutai": "【100株】【分割注意】オーナーズカード1％キャッシュバック",
    "yutai_syubetsu": "割引券",
    "restriction": "",
    "d_kenri": "2月末<br>8月31日",
    "updated": "2026-01-13T09:54:34.675077"
  },
  "8273": {
    "name": "イズミ",
    "zaiko": {
      "nikko": 2800,
      "kabucom": 71300,
      "rakuten": null,
      "sbi": null,
      "gmo": null,
      "matsui": 2,
      "monex": 1
    },
    "taisyaku": "貸借銘柄",
    "is_taishaku": true,
    "kabuka": 3020,
    "kabusu": 100,
    "max_gyaku": 2480,
    "gyaku_days": 1,
    "avg5_gyaku": 3.795,
    "haito": null,
    "gl_value": 600,
    "yutai": "【100株】買物券1000円相当もしくはギフトカード500円相当",
    "yutai_syubetsu": "買物券",
    "restriction": "",
    "d_kenri": "2月末日<br>8月31日",
    "updated": "2026-01-13T09:54:34.675081"
  },
  "8278": {
    "name": "フジ",
    "zaiko": {
      "nikko": 13900,
      "kabucom": null,
      "rakuten": 0,
      "sbi": null,
      "gmo": null,
      "matsui": null,
      "monex": 1
    },
    "taisyaku": "貸借銘柄",
    "is_taishaku": true,
    "kabuka": 2061,
    "kabusu": 500,
    "max_gyaku": 8400,
    "gyaku_days": 1,
    "avg5_gyaku": 7.37,
    "haito": null,
    "gl_value": 500,
    "yutai": "【300株】新米2kg【注：継続保有制限】",
    "yutai_syubetsu": "食べ物",
    "restriction": "",
    "d_kenri": "2月末日<br>8月31日",
    "updated": "2026-01-13T09:54:34.675085"
  },
  "8783": {
    "name": "ａｂｃ",
    "zaiko": {
      "nikko": null,
      "kabucom": null,
      "rakuten": null,
      "sbi": null,
      "gmo": null,
      "matsui": null,
      "monex": null
    },
    "taisyaku": "制度信用銘柄",
    "is_taishaku": false,
    "kabuka": 0,
    "kabusu": 100,
    "max_gyaku": 400,
    "gyaku_days": 1,
    "avg5_gyaku": 0.0,
    "haito": 0,
    "gl_value": 0,
    "yutai": "【100株】株主優待ポイント10000円相当",
    "yutai_syubetsu": "買物券",
    "restriction": "",
    "d_kenri": "8月31日",
    "updated": "2026-01-13T09:54:34.675088"
  },
  "8904": {
    "name": "ＡＶＡＮＴＩＡ",
    "zaiko": {
      "nikko": 0,
      "kabucom": null,
      "rakuten": null,
      "sbi": null,
      "gmo": null,
      "matsui": null,
      "monex": null
    },
    "taisyaku": "貸借銘柄",
    "is_taishaku": true,
    "kabuka": 871,
    "kabusu": 100,
    "max_gyaku": 720,
    "gyaku_days": 1,
    "avg5_gyaku": 4.15,
    "haito": 19,
    "gl_value": 950,
    "yutai": "【100株】クオカード 1000円相当【注：継続保有制限】",
    "yutai_syubetsu": "クオカード",
    "restriction": "",
    "d_kenri": "8月31日",
    "updated": "2026-01-13T09:54:34.675092"
  },
  "9241": {
    "name": "フューチャーリンクネットワーク",
    "zaiko": {
      "nikko": null,
      "kabucom": null,
      "rakuten": null,
      "sbi": null,
      "gmo": null,
      "matsui": null,
      "monex": null
    },
    "taisyaku": "制度信用銘柄",
    "is_taishaku": false,
    "kabuka": 1746,
    "kabusu": 100,
    "max_gyaku": 1440,
    "gyaku_days": 1,
    "avg5_gyaku": 0.0,
    "haito": 0,
    "gl_value": 3000,
    "yutai": "【100株】まいぷれのご当地ギフト5,000円相当",
    "yutai_syubetsu": "カタログギフト",
    "restriction": "",
    "d_kenri": "8月31日",
    "updated": "2026-01-13T09:54:34.675096"
  },
  "9252": {
    "name": "ラストワンマイル",
    "zaiko": {
      "nikko": null,
      "kabucom": null,
      "rakuten": null,
      "sbi": null,
      "gmo": null,
      "matsui": null,
      "monex": null
    },
    "taisyaku": "制度信用銘柄",
    "is_taishaku": false,
    "kabuka": 3970,
    "kabusu": 1,
    "max_gyaku": 32,
    "gyaku_days": 1,
    "avg5_gyaku": 0.0,
    "haito": 12,
    "gl_value": 970,
    "yutai": "【1株】【2025廃止】Amazonギフトカード1000円相当【注︰継続保有制限】",
    "yutai_syubetsu": "ギフトカード",
    "restriction": "",
    "d_kenri": "2月末<br>8月31日",
    "updated": "2026-01-13T09:54:34.675100"
  },
  "9326": {
    "name": "関通",
    "zaiko": {
      "nikko": null,
      "kabucom": null,
      "rakuten": null,
      "sbi": null,
      "gmo": null,
      "matsui": null,
      "monex": null
    },
    "taisyaku": "制度信用銘柄",
    "is_taishaku": false,
    "kabuka": 469,
    "kabusu": 700,
    "max_gyaku": 2800,
    "gyaku_days": 1,
    "avg5_gyaku": 0.0,
    "haito": null,
    "gl_value": 0,
    "yutai": "【700株】プレミアム優待クラブ3000ポイント",
    "yutai_syubetsu": "プレミアム優待クラブ",
    "restriction": "",
    "d_kenri": "8月31日",
    "updated": "2026-01-13T09:54:34.675103"
  },
  "9418": {
    "name": "Ｕ－ＮＥＸＴ　ＨＯＬＤＩＮＧＳ",
    "zaiko": {
      "nikko": 4900,
      "kabucom": 6700,
      "rakuten": 0,
      "sbi": null,
      "gmo": null,
      "matsui": 2,
      "monex": 1
    },
    "taisyaku": "貸借銘柄",
    "is_taishaku": true,
    "kabuka": 2026,
    "kabusu": 100,
    "max_gyaku": 1680,
    "gyaku_days": 1,
    "avg5_gyaku": 1.22,
    "haito": null,
    "gl_value": 0,
    "yutai": "【100株】U-NEXT90日分利用料及びポイント1000円分",
    "yutai_syubetsu": "自社サービス",
    "restriction": "",
    "d_kenri": "2月末日<br>8月31日",
    "updated": "2026-01-13T09:54:34.675108"
  },
  "9601": {
    "name": "松竹",
    "zaiko": {
      "nikko": 1200,
      "kabucom": 0,
      "rakuten": 0,
      "sbi": null,
      "gmo": null,
      "matsui": null,
      "monex": 1
    },
    "taisyaku": "貸借銘柄",
    "is_taishaku": true,
    "kabuka": 11830,
    "kabusu": 100,
    "max_gyaku": 9520,
    "gyaku_days": 1,
    "avg5_gyaku": 6.75,
    "haito": null,
    "gl_value": 0,
    "yutai": "【100株】映画招待ポイント　8回分",
    "yutai_syubetsu": "自社サービス",
    "restriction": "",
    "d_kenri": "2月末日<br>8月31日",
    "updated": "2026-01-13T09:54:34.675112"
  },
  "9602": {
    "name": "東宝",
    "zaiko": {
      "nikko": 1700,
      "kabucom": 14700,
      "rakuten": 0,
      "sbi": 1,
      "gmo": null,
      "matsui": 2,
      "monex": 2
    },
    "taisyaku": "貸借銘柄",
    "is_taishaku": true,
    "kabuka": 7800,
    "kabusu": 100,
    "max_gyaku": 6240,
    "gyaku_days": 1,
    "avg5_gyaku": 2.32,
    "haito": null,
    "gl_value": 1000,
    "yutai": "【100株】映画招待券 1枚",
    "yutai_syubetsu": "自社サービス",
    "restriction": "",
    "d_kenri": "2月末日<br>8月31日",
    "updated": "2026-01-13T09:54:34.675116"
  },
  "9612": {
    "name": "ラックランド",
    "zaiko": {
      "nikko": 0,
      "kabucom": null,
      "rakuten": 6900,
      "sbi": null,
      "gmo": null,
      "matsui": null,
      "monex": null
    },
    "taisyaku": "制度信用銘柄",
    "is_taishaku": false,
    "kabuka": 1878,
    "kabusu": 100,
    "max_gyaku": 1520,
    "gyaku_days": 1,
    "avg5_gyaku": 0.0,
    "haito": null,
    "gl_value": 2100,
    "yutai": "【100株】【2026廃止】東北地方名産品詰め合わせ 3500円相当",
    "yutai_syubetsu": "カタログギフト",
    "restriction": "",
    "d_kenri": "3月31日<br>8月31日<br>9月30日<br>2月末",
    "updated": "2026-01-13T09:54:34.675120"
  },
  "9661": {
    "name": "歌舞伎座",
    "zaiko": {
      "nikko": null,
      "kabucom": null,
      "rakuten": null,
      "sbi": null,
      "gmo": null,
      "matsui": null,
      "monex": null
    },
    "taisyaku": "制度信用銘柄",
    "is_taishaku": false,
    "kabuka": 0,
    "kabusu": 150,
    "max_gyaku": 600,
    "gyaku_days": 1,
    "avg5_gyaku": 0.0,
    "haito": null,
    "gl_value": 0,
    "yutai": "【150株】歌舞伎座招待券",
    "yutai_syubetsu": "自社サービス",
    "restriction": "",
    "d_kenri": "2月末日<br>8月31日",
    "updated": "2026-01-13T09:54:34.675124"
  },
  "9778": {
    "name": "昴",
    "zaiko": {
      "nikko": null,
      "kabucom": null,
      "rakuten": null,
      "sbi": null,
      "gmo": null,
      "matsui": null,
      "monex": null
    },
    "taisyaku": "制度信用銘柄",
    "is_taishaku": false,
    "kabuka": 0,
    "kabusu": 100,
    "max_gyaku": 400,
    "gyaku_days": 1,
    "avg5_gyaku": 0.0,
    "haito": null,
    "gl_value": 1500,
    "yutai": "【100株】３kgの青森産高級りんご",
    "yutai_syubetsu": "食べ物",
    "restriction": "",
    "d_kenri": "2月末日<br>8月31日",
    "updated": "2026-01-13T09:54:34.675128"
  },
  "9842": {
    "name": "アークランズ",
    "zaiko": {
      "nikko": 9000,
      "kabucom": null,
      "rakuten": 0,
      "sbi": null,
      "gmo": null,
      "matsui": null,
      "monex": 1
    },
    "taisyaku": "貸借銘柄",
    "is_taishaku": true,
    "kabuka": 1847,
    "kabusu": 100,
    "max_gyaku": 1520,
    "gyaku_days": 1,
    "avg5_gyaku": 2.925,
    "haito": null,
    "gl_value": 840,
    "yutai": "【100株】ご優待券1100円相当",
    "yutai_syubetsu": "買物券",
    "restriction": "",
    "d_kenri": "2月末<br>8月31日",
    "updated": "2026-01-13T09:54:34.675132"
  },
  "9846": {
    "name": "天満屋ストア",
    "zaiko": {
      "nikko": null,
      "kabucom": null,
      "rakuten": null,
      "sbi": null,
      "gmo": null,
      "matsui": null,
      "monex": null
    },
    "taisyaku": "制度信用銘柄",
    "is_taishaku": false,
    "kabuka": 976,
    "kabusu": 100,
    "max_gyaku": 800,
    "gyaku_days": 1,
    "avg5_gyaku": 0.0,
    "haito": null,
    "gl_value": 970,
    "yutai": "【100株】ＶＪＡギフトカード 1000円相当",
    "yutai_syubetsu": "ギフトカード",
    "restriction": "",
    "d_kenri": "2月末日<br>8月31日",
    "updated": "2026-01-13T09:54:34.675135"
  },
  "9861": {
    "name": "吉野家ホールディングス",
    "zaiko": {
      "nikko": 8600,
      "kabucom": 0,
      "rakuten": 0,
      "sbi": null,
      "gmo": 0,
      "matsui": null,
      "monex": 1
    },
    "taisyaku": "貸借銘柄",
    "is_taishaku": true,
    "kabuka": 3033,
    "kabusu": 200,
    "max_gyaku": 4960,
    "gyaku_days": 1,
    "avg5_gyaku": 3.74,
    "haito": null,
    "gl_value": 4100,
    "yutai": "【200株】食事券 5000円相当",
    "yutai_syubetsu": "買物券",
    "restriction": "",
    "d_kenri": "2月末日<br>8月31日",
    "updated": "2026-01-13T09:54:34.675140"
  },
  "9903": {
    "name": "カンセキ",
    "zaiko": {
      "nikko": null,
      "kabucom": null,
      "rakuten": null,
      "sbi": null,
      "gmo": null,
      "matsui": null,
      "monex": null
    },
    "taisyaku": "貸借銘柄",
    "is_taishaku": true,
    "kabuka": 878,
    "kabusu": 100,
    "max_gyaku": 720,
    "gyaku_days": 1,
    "avg5_gyaku": 12.53,
    "haito": null,
    "gl_value": 300,
    "yutai": "【100株】買物優待券（15%割引）",
    "yutai_syubetsu": "割引券",
    "restriction": "",
    "d_kenri": "2月末日<br>8月31日",
    "updated": "2026-01-13T09:54:34.675143"
  },
  "9946": {
    "name": "ミニストップ",
    "zaiko": {
      "nikko": 6400,
      "kabucom": null,
      "rakuten": 0,
      "sbi": null,
      "gmo": null,
      "matsui": null,
      "monex": null
    },
    "taisyaku": "貸借銘柄",
    "is_taishaku": true,
    "kabuka": 2144,
    "kabusu": 100,
    "max_gyaku": 1760,
    "gyaku_days": 1,
    "avg5_gyaku": 8.555,
    "haito": null,
    "gl_value": 1000,
    "yutai": "【100株】ソフトクリーム交換券5枚",
    "yutai_syubetsu": "買物券",
    "restriction": "",
    "d_kenri": "2月末日<br>8月31日",
    "updated": "2026-01-13T09:54:34.675147"
  },
  "9978": {
    "name": "文教堂グループホールディングス",
    "zaiko": {
      "nikko": null,
      "kabucom": null,
      "rakuten": null,
      "sbi": null,
      "gmo": null,
      "matsui": null,
      "monex": 1
    },
    "taisyaku": "制度信用銘柄",
    "is_taishaku": false,
    "kabuka": 0,
    "kabusu": 100,
    "max_gyaku": 400,
    "gyaku_days": 1,
    "avg5_gyaku": 0.0,
    "haito": 0,
    "gl_value": 400,
    "yutai": "【100株】商品購入時 5％割引優待",
    "yutai_syubetsu": "割引券",
    "restriction": "",
    "d_kenri": "2月末日<br>8月31日",
    "updated": "2026-01-13T09:54:34.675151"
  },
  "9979": {
    "name": "大庄",
    "zaiko": {
      "nikko": 0,
      "kabucom": null,
      "rakuten": 0,
      "sbi": null,
      "gmo": null,
      "matsui": null,
      "monex": 1
    },
    "taisyaku": "貸借銘柄",
    "is_taishaku": true,
    "kabuka": 1193,
    "kabusu": 100,
    "max_gyaku": 960,
    "gyaku_days": 1,
    "avg5_gyaku": 8.67,
    "haito": 8,
    "gl_value": 2100,
    "yutai": "【100株】食事券 3000円相当",
    "yutai_syubetsu": "買物券",
    "restriction": "",
    "d_kenri": "2月末日<br>8月31日",
    "updated": "2026-01-13T09:54:34.675154"
  },
  "9993": {
    "name": "ヤマザワ",
    "zaiko": {
      "nikko": 0,
      "kabucom": null,
      "rakuten": null,
      "sbi": null,
      "gmo": null,
      "matsui": null,
      "monex": 0
    },
    "taisyaku": "制度信用銘柄",
    "is_taishaku": false,
    "kabuka": 1184,
    "kabusu": 100,
    "max_gyaku": 960,
    "gyaku_days": 1,
    "avg5_gyaku": 0.0,
    "haito": null,
    "gl_value": 500,
    "yutai": "【100株】【山形・宮城以外】つや姫2kg【注：継続保有制限】",
    "yutai_syubetsu": "食べ物",
    "restriction": "",
    "d_kenri": "2月末日<br>8月31日",
    "updated": "2026-01-13T09:54:34.675158"
  },
  "3035": {
    "name": "ケイティケイ",
    "zaiko": {
      "nikko": null,
      "kabucom": null,
      "rakuten": null,
      "sbi": null,
      "gmo": null,
      "matsui": null,
      "monex": null
    },
    "taisyaku": "貸借銘柄",
    "is_taishaku": true,
    "kabuka": 652,
    "kabusu": 600,
    "max_gyaku": 3360,
    "gyaku_days": 1,
    "avg5_gyaku": 14.0,
    "haito": 9,
    "gl_value": 1800,
    "yutai": "【600株】プレミアム優待クラブ3000ポイント",
    "yutai_syubetsu": "プレミアム優待クラブ",
    "restriction": "",
    "d_kenri": "8月20日",
    "updated": "2026-01-13T09:54:34.675162"
  },
  "7545": {
    "name": "西松屋チェーン",
    "zaiko": {
      "nikko": 7400,
      "kabucom": null,
      "rakuten": null,
      "sbi": null,
      "gmo": 2,
      "matsui": null,
      "monex": 1
    },
    "taisyaku": "貸借銘柄",
    "is_taishaku": true,
    "kabuka": 2107,
    "kabusu": 100,
    "max_gyaku": 1760,
    "gyaku_days": 1,
    "avg5_gyaku": 4.515,
    "haito": null,
    "gl_value": 800,
    "yutai": "【100株】買物カード1000円相当",
    "yutai_syubetsu": "買物券",
    "restriction": "",
    "d_kenri": "2月20日<br>8月20日",
    "updated": "2026-01-13T09:54:34.675165"
  },
  "8276": {
    "name": "平和堂",
    "zaiko": {
      "nikko": 4800,
      "kabucom": 59500,
      "rakuten": null,
      "sbi": null,
      "gmo": 2,
      "matsui": null,
      "monex": 1
    },
    "taisyaku": "貸借銘柄",
    "is_taishaku": true,
    "kabuka": 2880,
    "kabusu": 100,
    "max_gyaku": 2320,
    "gyaku_days": 1,
    "avg5_gyaku": 3.36,
    "haito": null,
    "gl_value": 550,
    "yutai": "【100株】株主様ご優待券（割引券） 1000円相当",
    "yutai_syubetsu": "買物券",
    "restriction": "",
    "d_kenri": "2月20日<br>8月20日",
    "updated": "2026-01-13T09:54:34.675170"
  }
}